odoo/addons/project_forecast_line_deadline/README.rst
odoo/addons/project_forecast_line_deadline/__init__.py
odoo/addons/project_forecast_line_deadline/__manifest__.py
odoo/addons/project_forecast_line_deadline/i18n/es.po
odoo/addons/project_forecast_line_deadline/i18n/project_forecast_line_deadline.pot
odoo/addons/project_forecast_line_deadline/models/__init__.py
odoo/addons/project_forecast_line_deadline/models/project_task.py
odoo/addons/project_forecast_line_deadline/readme/CONTRIBUTORS.rst
odoo/addons/project_forecast_line_deadline/readme/DESCRIPTION.rst
odoo/addons/project_forecast_line_deadline/readme/USAGE.rst
odoo/addons/project_forecast_line_deadline/static/description/icon.png
odoo/addons/project_forecast_line_deadline/static/description/index.html
odoo/addons/project_forecast_line_deadline/tests/__init__.py
odoo/addons/project_forecast_line_deadline/tests/test_forecast_line_deadline.py
odoo_addon_project_forecast_line_deadline-15.0.1.0.0.3.dist-info/METADATA
odoo_addon_project_forecast_line_deadline-15.0.1.0.0.3.dist-info/WHEEL
odoo_addon_project_forecast_line_deadline-15.0.1.0.0.3.dist-info/top_level.txt
odoo_addon_project_forecast_line_deadline-15.0.1.0.0.3.dist-info/RECORD
